{"cookies": [], "origins": [{"origin": "https://nikita-filonov.github.io", "localStorage": [{"name": "persist:users", "value": "{\"user\":\"{\\\"id\\\":\\\"babde97e-d4bc-4ca6-83df-6ec9f82876cf\\\",\\\"email\\\":\\\"user.name@gmail.com\\\",\\\"username\\\":\\\"username\\\",\\\"password\\\":\\\"password\\\"}\",\"users\":\"[{\\\"id\\\":\\\"babde97e-d4bc-4ca6-83df-6ec9f82876cf\\\",\\\"email\\\":\\\"user.name@gmail.com\\\",\\\"username\\\":\\\"username\\\",\\\"password\\\":\\\"password\\\"}]\",\"_persist\":\"{\\\"version\\\":-1,\\\"rehydrated\\\":true}\"}"}, {"name": "persist:courses", "value": "{\"course\":\"{\\\"id\\\":\\\"\\\",\\\"title\\\":\\\"\\\",\\\"userId\\\":\\\"\\\",\\\"maxScore\\\":0,\\\"minScore\\\":0,\\\"exercises\\\":[],\\\"description\\\":\\\"\\\",\\\"previewImage\\\":null,\\\"estimatedTime\\\":\\\"\\\"}\",\"courses\":\"[]\",\"_persist\":\"{\\\"version\\\":-1,\\\"rehydrated\\\":true}\"}"}]}]}